MLGLUE/Likelihoods.py
MLGLUE/MLGLUE.py
MLGLUE/__init__.py
MLGLUE/version.py
mlglue-0.0.19.dist-info/LICENSE
mlglue-0.0.19.dist-info/METADATA
mlglue-0.0.19.dist-info/WHEEL
mlglue-0.0.19.dist-info/top_level.txt
mlglue-0.0.19.dist-info/RECORD
