Metadata-Version: 2.1
Name: mlglue
Version: 0.0.19
Summary: a Python implementation of the (M)ulti(l)evel (G)eneralized (L)ikelihood (U)ncertainty (E)stimation (MLGLUE) algorithm and utility functions
Home-page: https://github.com/iGW-TU-Dresden/MLGLUE
Author: M. G. Rudolph
Author-email: max_gustav.rudolph@tu-dresden.de
License: MIT
Platform: Windows
Classifier: Development Status :: 3 - Alpha
Classifier: Intended Audience :: Science/Research
Classifier: Intended Audience :: Other Audience
Classifier: License :: OSI Approved :: MIT License
Classifier: Programming Language :: Python :: 3.11
Classifier: Topic :: Scientific/Engineering :: Hydrology
License-File: LICENSE
Requires-Dist: numpy (>=1.23.5)
Requires-Dist: ray (>=2.2.0)
